tinydb_rust-0.9.0.dist-info/METADATA
tinydb_rust-0.9.0.dist-info/WHEEL
tinydb_rust-0.9.0.dist-info/licenses/LICENSE
tinydb_rust/__init__.py
tinydb_rust/_tinydb_core.abi3.so
tinydb_rust/_tinydb_core.pyi
tinydb_rust/middlewares.py
tinydb_rust/operations.py
tinydb_rust/py.typed
tinydb_rust/queries.py
tinydb_rust/storages.py
tinydb_rust/table.py
tinydb_rust/utils.py
tinydb_rust-0.9.0.dist-info/RECORD
