Metadata-Version: 2.4
Name: tinydb_rust
Version: 0.9.0
Classifier: Development Status :: 4 - Beta
Classifier: Intended Audience :: Developers
Classifier: License :: OSI Approved :: MIT License
Classifier: Programming Language :: Rust
Classifier: Programming Language :: Python :: 3
Classifier: Programming Language :: Python :: 3.8
Classifier: Programming Language :: Python :: 3.9
Classifier: Programming Language :: Python :: 3.10
Classifier: Programming Language :: Python :: 3.11
Classifier: Programming Language :: Python :: 3.12
Requires-Dist: maturin>=1.10.1 ; extra == 'dev'
Requires-Dist: pytest>=7.0 ; extra == 'dev'
Requires-Dist: pyyaml>=6.0.3 ; extra == 'dev'
Requires-Dist: ruff>=0.14.6 ; extra == 'dev'
Requires-Dist: tinydb>=4.8.2 ; extra == 'dev'
Provides-Extra: dev
License-File: LICENSE
Summary: A Rust reimplementation of the TinyDB library
Keywords: database,tinydb,json,nosql
Author-email: morninghao <morning.haoo@gmail.com>
License: MIT
Requires-Python: >=3.8
